XinshounianlaiYiyeZhijianGaibianNideGuanggao/README.md
XinshounianlaiYiyeZhijianGaibianNideGuanggao/__init__.py
XinshounianlaiYiyeZhijianGaibianNideGuanggao/__main__.py
XinshounianlaiYiyeZhijianGaibianNideGuanggao/file.pdf
XinshounianlaiYiyeZhijianGaibianNideGuanggao/index.html
xinshounianlai_yiye_zhijian_gaibian_nide_guanggao-2022.10.10.0.dist-info/METADATA
xinshounianlai_yiye_zhijian_gaibian_nide_guanggao-2022.10.10.0.dist-info/WHEEL
xinshounianlai_yiye_zhijian_gaibian_nide_guanggao-2022.10.10.0.dist-info/entry_points.txt
xinshounianlai_yiye_zhijian_gaibian_nide_guanggao-2022.10.10.0.dist-info/top_level.txt
xinshounianlai_yiye_zhijian_gaibian_nide_guanggao-2022.10.10.0.dist-info/RECORD
